LICENSE
README.md
setup.cfg
setup.py
./functions/__init__.py
./functions/calculate_diff_scores.py
./functions/data_loaders.py
./functions/extract_LS_embedding.py
./functions/find_motifs.py
./functions/heatmap.py
./functions/mutate.py
./functions/predict.py
./functions/preprocess.py
./functions/single_resolution_importance.py
./functions/train.py
./functions/utils.py
./functions/src/__init__.py
./functions/src/transformers/__init__.py
./functions/src/transformers/activations.py
./functions/src/transformers/configuration_albert.py
./functions/src/transformers/configuration_auto.py
./functions/src/transformers/configuration_bart.py
./functions/src/transformers/configuration_bert.py
./functions/src/transformers/configuration_camembert.py
./functions/src/transformers/configuration_ctrl.py
./functions/src/transformers/configuration_distilbert.py
./functions/src/transformers/configuration_flaubert.py
./functions/src/transformers/configuration_gpt2.py
./functions/src/transformers/configuration_mmbt.py
./functions/src/transformers/configuration_openai.py
./functions/src/transformers/configuration_roberta.py
./functions/src/transformers/configuration_t5.py
./functions/src/transformers/configuration_transfo_xl.py
./functions/src/transformers/configuration_utils.py
./functions/src/transformers/configuration_xlm.py
./functions/src/transformers/configuration_xlm_roberta.py
./functions/src/transformers/configuration_xlnet.py
./functions/src/transformers/convert_albert_original_tf_checkpoint_to_pytorch.py
./functions/src/transformers/convert_bart_original_pytorch_checkpoint_to_pytorch.py
./functions/src/transformers/convert_bert_original_tf_checkpoint_to_pytorch.py
./functions/src/transformers/convert_bert_pytorch_checkpoint_to_original_tf.py
./functions/src/transformers/convert_gpt2_original_tf_checkpoint_to_pytorch.py
./functions/src/transformers/convert_openai_original_tf_checkpoint_to_pytorch.py
./functions/src/transformers/convert_pytorch_checkpoint_to_tf2.py
UTRBERT.egg-info/PKG-INFO
UTRBERT.egg-info/SOURCES.txt
UTRBERT.egg-info/dependency_links.txt
UTRBERT.egg-info/requires.txt
UTRBERT.egg-info/top_level.txt