Metadata-Version: 2.1
Name: UTRBERT
Version: 1.0.1
Summary: Deciphering 3'UTR mediated gene regulation using interpretable deep representation learning
Home-page: https://github.com/yangyn533/3UTRBERT
Author: Yuning Yang, Gen Li, Kuan Pang, Wuxinhao Cao, Xiangtao Li, and Zhaolei Zhang
Author-email: yyn.yang@mail.utoronto.ca
License: MIT
Keywords: NLP deep learning transformer pytorch tensorflow RNA 3utr bert
Platform: UNKNOWN
Classifier: Development Status :: 5 - Production/Stable
Classifier: Intended Audience :: Developers
Classifier: Intended Audience :: Education
Classifier: Intended Audience :: Science/Research
Classifier: License :: OSI Approved :: MIT License
Classifier: Operating System :: OS Independent
Classifier: Programming Language :: Python :: 3
Classifier: Programming Language :: Python :: 3.5
Classifier: Programming Language :: Python :: 3.6
Classifier: Programming Language :: Python :: 3.7
Classifier: Programming Language :: Python :: 3.8
Classifier: Programming Language :: Python :: 3.9
Classifier: Programming Language :: Python :: 3.10
Classifier: Topic :: Scientific/Engineering :: Artificial Intelligence
Requires-Python: >=3.5.0
License-File: LICENSE
